README.md
setup.py
sisepuede_calibration/__init__.py
sisepuede_calibration/calibration_lac.py
sisepuede_calibration/optimization_algorithms.py
sisepuede_calibration/transformation_lac.py
sisepuede_calibration.egg-info/PKG-INFO
sisepuede_calibration.egg-info/SOURCES.txt
sisepuede_calibration.egg-info/dependency_links.txt
sisepuede_calibration.egg-info/requires.txt
sisepuede_calibration.egg-info/top_level.txt
sisepuede_calibration/calibration_decorators/__init__.py
sisepuede_calibration/calibration_decorators/calib_decorators.py
sisepuede_calibration/calibration_decorators/dec_build_data_all_period_sector.py
sisepuede_calibration/calibration_decorators/dec_build_data_sector.py
sisepuede_calibration/calibration_decorators/dec_get_output_data.py
sisepuede_calibration/calibration_decorators/dec_performance_metrics.py
sisepuede_calibration/calibration_decorators/dec_performance_metrics_test_set.py
sisepuede_calibration/transformation_decorators/__init__.py