Metadata-Version: 2.1
Name: sisepuede-calibration
Version: 0.0.2
Summary: SISEPUEDE model calibration
Home-page: https://github.com/milocortes/sisepuede_calibration.git
Author: Hermilo Cortés
Author-email: hermilocg@tec.com
License: UNKNOWN
Platform: UNKNOWN
Classifier: Development Status :: 4 - Beta
Classifier: Programming Language :: Python :: 3
Classifier: Operating System :: OS Independent
Requires-Python: >=3
